dockerpal/__init__.py
dockerpal/__main__.py
dockerpal/app.py
dockerpal/cli.py
dockerpal/fsm.py
dockerpal-0.0.25.dist-info/licenses/LICENSE
dockerpal-0.0.25.dist-info/METADATA
dockerpal-0.0.25.dist-info/WHEEL
dockerpal-0.0.25.dist-info/entry_points.txt
dockerpal-0.0.25.dist-info/top_level.txt
dockerpal-0.0.25.dist-info/RECORD
