Metadata-Version: 2.4
Name: dockerpal
Version: 0.0.25
Summary: Docker images cleaner and inspector tui app
Home-page: https://github.com/yell0w4x/dockerpal
Author: yell0w4x
Author-email: yell0w4x@gmail.com
License: MIT
Project-URL: Bug Tracker, https://github.com/yell0w4x/dockerpal/issues
Keywords: docker images cleaner inspector tui
Classifier: Programming Language :: Python :: 3
Classifier: Operating System :: OS Independent
Requires-Python: >=3.11
License-File: LICENSE
Requires-Dist: certifi==2025.11.12
Requires-Dist: charset-normalizer==3.4.4
Requires-Dist: docker==7.1.0
Requires-Dist: idna==3.11
Requires-Dist: linkify-it-py==2.0.3
Requires-Dist: markdown-it-py==4.0.0
Requires-Dist: mdit-py-plugins==0.5.0
Requires-Dist: mdurl==0.1.2
Requires-Dist: platformdirs==4.5.1
Requires-Dist: Pygments==2.19.2
Requires-Dist: requests==2.32.5
Requires-Dist: rich==14.2.0
Requires-Dist: textual==6.12.0
Requires-Dist: tree-sitter==0.25.2
Requires-Dist: tree-sitter-bash==0.25.1
Requires-Dist: tree-sitter-css==0.25.0
Requires-Dist: tree-sitter-go==0.25.0
Requires-Dist: tree-sitter-html==0.23.2
Requires-Dist: tree-sitter-java==0.23.5
Requires-Dist: tree-sitter-javascript==0.25.0
Requires-Dist: tree-sitter-json==0.24.8
Requires-Dist: tree-sitter-markdown==0.5.1
Requires-Dist: tree-sitter-python==0.25.0
Requires-Dist: tree-sitter-regex==0.25.0
Requires-Dist: tree-sitter-rust==0.24.0
Requires-Dist: tree-sitter-sql==0.3.11
Requires-Dist: tree-sitter-toml==0.7.0
Requires-Dist: tree-sitter-xml==0.7.0
Requires-Dist: tree-sitter-yaml==0.7.2
Requires-Dist: typing_extensions==4.15.0
Requires-Dist: uc-micro-py==1.0.3
Requires-Dist: urllib3==2.6.2
Dynamic: license-file
